nixl_cu13/py.typed
nixl_cu13/_api.py
nixl_cu13/_bindings.cpython-314-aarch64-linux-gnu.so
nixl_cu13/logging.py
nixl_cu13/__init__.py
nixl_cu13/_utils.cpython-314-aarch64-linux-gnu.so
.nixl_cu13.mesonpy.libs/libucx_utils.so
.nixl_cu13.mesonpy.libs/libpull.so.1.3.0
.nixl_cu13.mesonpy.libs/libserdes.so
.nixl_cu13.mesonpy.libs/libstream.so
.nixl_cu13.mesonpy.libs/libcore.so.1.3.0
.nixl_cu13.mesonpy.libs/libnixl.so
.nixl_cu13.mesonpy.libs/libnixl_common.so
.nixl_cu13.mesonpy.libs/libfile_utils.so
.nixl_cu13.mesonpy.libs/libnixl_build.so
.nixl_cu13.mesonpy.libs/libnixl_test_utils.so
.nixl_cu13.mesonpy.libs/plugins/libplugin_GPUNETIO.so
.nixl_cu13.mesonpy.libs/plugins/libplugin_GDS_MT.so
.nixl_cu13.mesonpy.libs/plugins/libplugin_LIBFABRIC.so
.nixl_cu13.mesonpy.libs/plugins/libplugin_UCX.so
.nixl_cu13.mesonpy.libs/plugins/libplugin_POSIX.so
.nixl_cu13.mesonpy.libs/plugins/libplugin_GDS.so
.nixl_cu13.mesonpy.libs/plugins/libplugin_OBJ.so
.nixl_cu13.mesonpy.libs/plugins/libplugin_GUSLI.so
.nixl_cu13.mesonpy.libs/plugins/libtelemetry_exporter_prometheus.so
nixl_cu13-0.9.0.data/scripts/telemetry_reader
nixl_cu13-0.9.0.data/scripts/nixl_etcd_example
nixl_cu13-0.9.0.data/scripts/nixl_example
nixl_cu13-0.9.0.data/headers/asio.hpp
nixl_cu13-0.9.0.data/headers/asio/stream_file.hpp
nixl_cu13-0.9.0.data/headers/asio/basic_io_object.hpp
nixl_cu13-0.9.0.data/headers/asio/deferred.hpp
nixl_cu13-0.9.0.data/headers/asio/streambuf.hpp
nixl_cu13-0.9.0.data/headers/asio/basic_waitable_timer.hpp
nixl_cu13-0.9.0.data/headers/asio/cancellation_type.hpp
nixl_cu13-0.9.0.data/headers/asio/random_access_file.hpp
nixl_cu13-0.9.0.data/headers/asio/wait_traits.hpp
nixl_cu13-0.9.0.data/headers/asio/writable_pipe.hpp
nixl_cu13-0.9.0.data/headers/asio/basic_file.hpp
nixl_cu13-0.9.0.data/headers/asio/multiple_exceptions.hpp
nixl_cu13-0.9.0.data/headers/asio/system_executor.hpp
nixl_cu13-0.9.0.data/headers/asio/buffered_read_stream_fwd.hpp
nixl_cu13-0.9.0.dist-info/RECORD
nixl_cu13-0.9.0.dist-info/WHEEL
nixl_cu13-0.9.0.dist-info/METADATA
nixl_cu13-0.9.0.dist-info/licenses/LICENSE
nixl_cu13-0.9.0.dist-info/sboms/auditwheel.cdx.json
