Metadata-Version: 2.4
Name: nixl-cu13
Version: 0.9.0
Summary: NIXL Python API
Author-Email: NIXL Developers <nixl-developers@nvidia.com>
License-Expression: MIT AND Apache-2.0
License-File: LICENSE
Requires-Python: >=3.10
Requires-Dist: torch
Requires-Dist: numpy
